source2prompt/__init__.py
source2prompt/s2p.py
source2prompt-0.3.2.dist-info/METADATA
source2prompt-0.3.2.dist-info/WHEEL
source2prompt-0.3.2.dist-info/entry_points.txt
source2prompt-0.3.2.dist-info/top_level.txt
source2prompt-0.3.2.dist-info/RECORD
