Metadata-Version: 2.4
Name: source2prompt
Version: 0.3.2
Summary: A simple tool to convert source files to a single prompt file for LLMs
Home-page: https://github.com/IchigoHydrogen/source2prompt
Author: IchigoHydrogen
Classifier: Programming Language :: Python :: 3
Classifier: License :: OSI Approved :: MIT License
Classifier: Operating System :: OS Independent
Requires-Python: >=3.10
Requires-Dist: charset_normalizer
Requires-Dist: pathspec
Dynamic: author
Dynamic: classifier
Dynamic: description
Dynamic: description-content-type
Dynamic: home-page
Dynamic: requires-dist
Dynamic: requires-python
Dynamic: summary
